mathsvg/__init__.py
mathsvg/code-check.py
mathsvg/mathsvg.py
mathsvg/tests.py
mathsvg-0.4.0.dist-info/LICENSE
mathsvg-0.4.0.dist-info/METADATA
mathsvg-0.4.0.dist-info/WHEEL
mathsvg-0.4.0.dist-info/top_level.txt
mathsvg-0.4.0.dist-info/RECORD
