Metadata-Version: 2.1
Name: mathsvg
Version: 0.4.0
Summary: Mathematics oriented SVG creation
Home-page: http://github.com/alexn11/mathsvg
Author: Alexandre De Zotti
Author-email: alexn11.gh@gmail.com
License: MIT
Platform: UNKNOWN
Classifier: Programming Language :: Python :: 3
Classifier: License :: OSI Approved :: MIT License
Classifier: Operating System :: OS Independent
License-File: LICENSE
Requires-Dist: svgwrite
